{
  "conflicting": {

  },
  "long_description": "= DESCRIPTION:\n\n= REQUIREMENTS:\n\n= ATTRIBUTES: \n\n= USAGE:\n\n",
  "description": "Installs logwatch, a nice log analyzer",
  "providing": {

  },
  "maintainer": "Opscode, Inc.",
  "attributes": {

  },
  "replacing": {

  },
  "dependencies": {
    "perl": [

    ]
  },
  "maintainer_email": "cookbooks@opscode.com",
  "groupings": {

  },
  "recommendations": {

  },
  "platforms": {
    "debian": [

    ],
    "centos": [

    ],
    "ubuntu": [

    ],
    "redhat": [

    ]
  },
  "version": "0.1.1",
  "license": "Apache 2.0",
  "name": "logwatch",
  "suggestions": {

  },
  "recipes": {
    "logwatch": "Installs logwatch"
  }
}